{"size":5,"blockSize":300,"terrains":[{"angle":0,"type":1,"x":0,"y":0,"size":300},{"angle":0,"type":1,"x":600,"y":0,"size":300},{"angle":0,"type":1,"x":300,"y":0,"size":300},{"angle":0,"type":1,"x":0,"y":300,"size":300}],"rects":[],"bushes":[{"changed":false,"opacity":0.9,"active":true,"hitAnimateTimer":0,"hitAnimateShiftX":0,"hitAnimateShiftY":0,"id":0,"x":413.109375,"y":467,"size":100,"radius":50}],"rocks":[{"changed":false,"opacity":1,"active":true,"hitAnimateTimer":0,"hitAnimateShiftX":0,"hitAnimateShiftY":0,"id":0,"x":110.109375,"y":425,"size":100,"radius":50},{"changed":false,"opacity":1,"active":true,"hitAnimateTimer":0,"hitAnimateShiftX":0,"hitAnimateShiftY":0,"id":1,"x":205.109375,"y":86,"size":100,"radius":50},{"changed":false,"opacity":1,"active":true,"hitAnimateTimer":0,"hitAnimateShiftX":0,"hitAnimateShiftY":0,"id":2,"x":562.109375,"y":80,"size":100,"radius":50}],"trees":[]}